{
    "The Watcher in the Woods(1980)": 4.2,
    "Superman II(1980)": 4.1,
    "Where the Buffalo Roam(1980)": 4.0,
    "Popeye(1980)": 3.9,
    "The Private Eyes(1980)": 3.8,
    "When Time Ran Out...(1980)": 3.8,
    "The Island(1980)": 3.7,
    "City of Women(1980)": 3.6,
    "Blow Out(1981)": 3.5,
    "Little Darlings(1980)": 3.5,
    "The Awakening(1980)": 3.4,
    "The Nude Bomb(1980)": 3.4,
    "Honeysuckle Rose(1980)": 3.3,
    "Gilda Live(1980)": 3.2,
    "Prom Night(1980)": 3.2,
    "Roadie(1980)": 3.2,
    "The Competition(1980)": 3.2,
    "Any Which Way You Can(1980)": 3.1,
    "Seems Like Old Times(1980)": 3.1,
    "Stardust Memories(1980)": 3.1,
    "The Blues Brothers(1980)": 3.1,
    "The Boogey Man(1980)": 3.1,
    "The Octagon(1980)": 3.1,
    "9 to 5(1980)": 3.0,
    "Babylon(1980)": 3.0,
    "Can't Stop the Music(1980)": 3.0,
    "Oh, God! Book II(1980)": 3.0,
    "Raging Bull(1980)": 3.0,
    "Stir Crazy(1980)": 3.0,
    "Windows(1980)": 3.0,
    "Windwalker(1980)": 3.0,
    "Altered States(1980)": 2.9,
    "Escape from New York(1981)": 2.9,
    "It's My Turn(1980)": 2.9,
    "Loving Couples(1980)": 2.9,
    "Oh Heavenly Dog(1980)": 2.9,
    "The King and the Mockingbird(1980)": 2.9,
    "Xanadu(1980)": 2.9,
    "Airplane!(1980)": 2.8,
    "Cattle Annie and Little Britches(1980)": 2.8,
    "Cheech and Chong's Next Movie(1980)": 2.8,
    "Fatso(1980)": 2.8,
    "Mantis Fist Fighter(1980)": 2.8,
    "Resurrection(1980)": 2.8,
    "The Evil Dead(1981)": 2.8,
    "Willie & Phil(1980)": 2.8,
    "Brubaker(1980)": 2.7,
    "Caddyshack(1980)": 2.7,
    "Fame(1980)": 2.7,
    "Phobia(1980)": 2.7,
    "Smokey and the Bandit II(1980)": 2.7,
    "Star Wars: Episode V - The Empire Strikes Back(1980)": 2.7,
    "The Final Countdown(1980)": 2.7,
    "The Hollywood Knights(1980)": 2.7,
    "Heaven's Gate(1980)": 2.6,
    "Ordinary People(1980)": 2.6,
    "Serial(1980)": 2.6,
    "The Long Riders(1980)": 2.6,
    "Indiana Jones and the Raiders of the Lost Ark(1981)": 2.5,
    "Melvin and Howard(1980)": 2.5,
    "Raise the Titanic(1980)": 2.5,
    "The Stunt Man(1980)": 2.5,
    "Moscow Does Not Believe in Tears(1980)": 2.4,
    "The Gong Show Movie(1980)": 2.4,
    "Coal Miner's Daughter(1980)": 2.3,
    "Wholly Moses!(1980)": 2.3,
    "Lion of the Desert(1980)": 2.2,
    "The Gods Must Be Crazy(1980)": 2.2,
    "Hangar 18(1980)": 2.1,
    "Porky's(1981)": 2.1,
    "My Bodyguard(1980)": 2.0,
    "The Fog(1980)": 2.0,
    "Motel Hell(1980)": 1.6,
    "The Blue Lagoon(1980)": 1.5,
    "The Jazz Singer(1980)": 1.3,
    "Hero at Large(1980)": 0.7,
    "In God We Trust (or Gimme That Prime Time Religion)(1980)": 0.7
}